aioze/__init__.py
aioze/access.py
aioze/ozeapiclient.py
aioze/api/__init__.py
aioze/api/email.py
aioze/api/event.py
aioze/api/grade.py
aioze/api/homework.py
aioze/api/information.py
aioze/api/notification.py
aioze/api/punishment.py
aioze/api/userinfo.py
aioze-0.0.5.dist-info/LICENSE.txt
aioze-0.0.5.dist-info/METADATA
aioze-0.0.5.dist-info/WHEEL
aioze-0.0.5.dist-info/top_level.txt
aioze-0.0.5.dist-info/RECORD
