Metadata-Version: 2.1
Name: aioze
Version: 0.0.5
Summary: Python wrapper for the oZe ENT http API
License: Apache
Project-URL: Bug Tracker, https://github.com/lesensei/aioze/issues
Project-URL: Source Code, https://github.com/lesensei/aioze
Keywords: oZe,ENT,ENC,API
Platform: UNKNOWN
Classifier: Framework :: aiohttp
Classifier: Programming Language :: Python :: 3
License-File: LICENSE.txt
Requires-Dist: aiohttp
Requires-Dist: async-timeout
Requires-Dist: python-dateutil
Requires-Dist: requests
